meshtastic_flasher/__init__.py
meshtastic_flasher/admin_form.py
meshtastic_flasher/advanced_form.py
meshtastic_flasher/channel_form.py
meshtastic_flasher/channel_settings.py
meshtastic_flasher/cog.svg
meshtastic_flasher/esptool_form.py
meshtastic_flasher/fields.json
meshtastic_flasher/fixed_position_form.py
meshtastic_flasher/form.py
meshtastic_flasher/help.svg
meshtastic_flasher/info.svg
meshtastic_flasher/info_form.py
meshtastic_flasher/logo.png
meshtastic_flasher/main.py
meshtastic_flasher/meshtastic_theme.xml
meshtastic_flasher/options.svg
meshtastic_flasher/plugin_settings.py
meshtastic_flasher/plugins_canned_message_form.py
meshtastic_flasher/plugins_external_notifications_form.py
meshtastic_flasher/plugins_range_test_form.py
meshtastic_flasher/plugins_rotary_encoder_form.py
meshtastic_flasher/plugins_serial_form.py
meshtastic_flasher/plugins_store_and_forward_form.py
meshtastic_flasher/plugins_telemetry_form.py
meshtastic_flasher/position_form.py
meshtastic_flasher/power_form.py
meshtastic_flasher/radio_form.py
meshtastic_flasher/radio_picker_form.py
meshtastic_flasher/send_text_form.py
meshtastic_flasher/settings.py
meshtastic_flasher/user_form.py
meshtastic_flasher/util.py
meshtastic_flasher/version.py
meshtastic_flasher/wifi_and_mqtt_form.py
meshtastic_flasher/radios/heltec-v1.png
meshtastic_flasher/radios/heltec-v2.0.png
meshtastic_flasher/radios/heltec-v2.1.jpg
meshtastic_flasher/radios/meshtastic-diy.jpg
meshtastic_flasher/radios/nano-g1.jpeg
meshtastic_flasher/radios/rak11200.jpg
meshtastic_flasher/radios/rak4631_19003.png
meshtastic_flasher/radios/rak4631_5005.png
meshtastic_flasher/radios/rak4631_5005_epaper.jpg
meshtastic_flasher/radios/t-beam-v0.7.png
meshtastic_flasher/radios/t-beam.png
meshtastic_flasher/radios/t-echo.jpeg
meshtastic_flasher/radios/tlora-v1.png
meshtastic_flasher/radios/tlora-v1_3.png
meshtastic_flasher/radios/tlora-v2.1-1.6.png
meshtastic_flasher/radios/tlora-v2.png
meshtastic_flasher-2.0.2.dist-info/LICENSE
meshtastic_flasher-2.0.2.dist-info/METADATA
meshtastic_flasher-2.0.2.dist-info/WHEEL
meshtastic_flasher-2.0.2.dist-info/entry_points.txt
meshtastic_flasher-2.0.2.dist-info/top_level.txt
meshtastic_flasher-2.0.2.dist-info/RECORD
