Metadata-Version: 2.1
Name: meshtastic-flasher
Version: 2.0.2
Summary: Graphical user interface to flash Meshtastic firmware to devices
Home-page: https://github.com/meshtastic/Meshtastic-gui-installer
Author: Meshtastic Developers
Author-email: contact@meshtastic.org
License: GPL-3.0-only
Classifier: License :: OSI Approved :: GNU General Public License v3 (GPLv3)
Classifier: Development Status :: 4 - Beta
Classifier: Programming Language :: Python :: 3
Classifier: Programming Language :: Python :: 3.6
Classifier: Programming Language :: Python :: 3.7
Classifier: Programming Language :: Python :: 3.8
Classifier: Programming Language :: Python :: 3.9
Classifier: Programming Language :: Python :: 3.10
Requires-Python: >=3.6
License-File: LICENSE
Requires-Dist: pyside6
Requires-Dist: PyGithub
Requires-Dist: esptool (==4.2.1)
Requires-Dist: meshtastic (>=2.0.8)
Requires-Dist: qt-material
Requires-Dist: psutil
Requires-Dist: adafruit-nrfutil
Requires-Dist: pyserial
Requires-Dist: geocoder
